LICENSE.md
MANIFEST.in
README.md
setup.py
publicstatic/__init__.py
publicstatic/__main__.py
publicstatic/builders.py
publicstatic/cache.py
publicstatic/cli.py
publicstatic/conf.py
publicstatic/const.py
publicstatic/errors.py
publicstatic/formatter.py
publicstatic/helpers.py
publicstatic/images.py
publicstatic/logger.py
publicstatic/markdown.py
publicstatic/minify.py
publicstatic/publicstatic.py
publicstatic/source.py
publicstatic/templates.py
publicstatic/urlify.py
publicstatic/version.py
publicstatic.egg-info/PKG-INFO
publicstatic.egg-info/SOURCES.txt
publicstatic.egg-info/dependency_links.txt
publicstatic.egg-info/entry_points.txt
publicstatic.egg-info/not-zip-safe
publicstatic.egg-info/requires.txt
publicstatic.egg-info/top_level.txt
publicstatic/prototype/.editorconfig
publicstatic/prototype/.gitignore
publicstatic/prototype/Guardfile
publicstatic/prototype/assets/humans.txt
publicstatic/prototype/assets/robots.txt
publicstatic/prototype/images/.gitignore
publicstatic/prototype/pages/about.md
publicstatic/prototype/posts/20101010-welcome.md
publicstatic/prototype/theme/assets/favicon.png
publicstatic/prototype/theme/assets/css/custom.css
publicstatic/prototype/theme/templates/_macros.html
publicstatic/prototype/theme/templates/archive.html
publicstatic/prototype/theme/templates/atom.xml
publicstatic/prototype/theme/templates/page.html
publicstatic/prototype/theme/templates/post.html
publicstatic/prototype/theme/templates/sitemap.xml
publicstatic/prototype/theme/templates/tag.html